cammello/__about__.py
cammello/__init__.py
cammello/cammello.py
cammello/res/cammello.png
cammello-0.0.2.dist-info/LICENSE
cammello-0.0.2.dist-info/METADATA
cammello-0.0.2.dist-info/WHEEL
cammello-0.0.2.dist-info/top_level.txt
cammello-0.0.2.dist-info/RECORD
