Metadata-Version: 2.1
Name: cammello
Version: 0.0.2
Summary: Un cammello.
Home-page: https://github.com/LucaMingarelli/cammello
Author: Luca Mingarelli
Author-email: lucamingarelli@me.com
License: MIT
Classifier: Programming Language :: Python :: 3
Classifier: License :: OSI Approved :: MIT License
Classifier: Operating System :: OS Independent
Requires-Python: >=3.6
License-File: LICENSE
